iterproxy/__init__.py
iterproxy/_version.py
iterproxy/iterproxy.py
iterproxy/docs/__init__.py
iterproxy/tests/__init__.py
iterproxy-0.3.1.dist-info/AUTHORS.rst
iterproxy-0.3.1.dist-info/LICENSE.txt
iterproxy-0.3.1.dist-info/METADATA
iterproxy-0.3.1.dist-info/WHEEL
iterproxy-0.3.1.dist-info/top_level.txt
iterproxy-0.3.1.dist-info/RECORD
