Metadata-Version: 2.1
Name: iterproxy
Version: 0.3.1
Summary: Give any iterable object capability to use .one(), .one_or_none(), .many(k), .skip(k), .all() API.
Home-page: https://github.com/MacHu-GWU/iterproxy-project
Download-URL: https://pypi.python.org/pypi/iterproxy/0.3.1#downloads
Author: Sanhe Hu
Author-email: husanhe@gmail.com
Maintainer: Unknown
License: MIT
Platform: Windows
Platform: MacOS
Platform: Unix
Classifier: Development Status :: 4 - Beta
Classifier: Intended Audience :: Developers
Classifier: License :: OSI Approved :: MIT License
Classifier: Natural Language :: English
Classifier: Operating System :: Microsoft :: Windows
Classifier: Operating System :: MacOS
Classifier: Operating System :: Unix
Classifier: Programming Language :: Python
Classifier: Programming Language :: Python :: 3.7
Classifier: Programming Language :: Python :: 3.8
Classifier: Programming Language :: Python :: 3.9
Classifier: Programming Language :: Python :: 3.10
Classifier: Programming Language :: Python :: 3.11
Classifier: Programming Language :: Python :: 3 :: Only
License-File: LICENSE.txt
License-File: AUTHORS.rst
Provides-Extra: docs
Requires-Dist: sphinx (==4.3.0) ; extra == 'docs'
Requires-Dist: sphinx-inline-tabs (==2021.8.17b10) ; extra == 'docs'
Requires-Dist: sphinx-jinja (==1.1.1) ; extra == 'docs'
Requires-Dist: sphinx-copybutton (==0.4.0) ; extra == 'docs'
Requires-Dist: rstobj (==1.2.1) ; extra == 'docs'
Requires-Dist: docfly (==1.0.2) ; extra == 'docs'
Requires-Dist: furo (==2021.8.31) ; extra == 'docs'
Provides-Extra: tests
Requires-Dist: pytest ; extra == 'tests'
Requires-Dist: pytest-cov ; extra == 'tests'
